django_search_autocomplete-0.1.1.dist-info/licenses/LICENSE
search_autocomplete/__init__.py
search_autocomplete/forms.py
search_autocomplete/urls.py
search_autocomplete/views.py
search_autocomplete/static/css/search-autocomplete.css
search_autocomplete/static/js/search-autocomplete.js
search_autocomplete/static/search_autocomplete/css/search-autocomplete.css
search_autocomplete/static/search_autocomplete/js/search-autocomplete.js
search_autocomplete/templates/search_autocomplete/config.html
django_search_autocomplete-0.1.1.dist-info/METADATA
django_search_autocomplete-0.1.1.dist-info/WHEEL
django_search_autocomplete-0.1.1.dist-info/top_level.txt
django_search_autocomplete-0.1.1.dist-info/RECORD
